python_package/__init__.py
python_package/ensinfo.py
ensinfo-0.0.1.dist-info/LICENSE
ensinfo-0.0.1.dist-info/METADATA
ensinfo-0.0.1.dist-info/WHEEL
ensinfo-0.0.1.dist-info/top_level.txt
ensinfo-0.0.1.dist-info/RECORD
